env_loader_pro/__init__.py
env_loader_pro/cli.py
env_loader_pro/loader.py
env_loader_pro/schema.py
env_loader_pro/utils.py
env_loader_pro-0.3.0.dist-info/licenses/LICENSE
env_loader_pro-0.3.0.dist-info/METADATA
env_loader_pro-0.3.0.dist-info/WHEEL
env_loader_pro-0.3.0.dist-info/entry_points.txt
env_loader_pro-0.3.0.dist-info/top_level.txt
env_loader_pro-0.3.0.dist-info/RECORD
