Metadata-Version: 2.4
Name: env-loader-pro
Version: 0.3.0
Summary: A typed, validated, and secure environment loader for Python projects with automatic type casting, validation, secret masking, and schema support.
Author-email: Shanen Thomas <shanen.j.thomas@gmail.com>
License-Expression: Apache-2.0
Project-URL: Homepage, https://github.com/shanen28/env-loader-pro
Project-URL: Documentation, https://github.com/shanen28/env-loader-pro#readme
Project-URL: Repository, https://github.com/shanen28/env-loader-pro
Project-URL: Bug Tracker, https://github.com/shanen28/env-loader-pro/issues
Keywords: env,dotenv,config,loader,validation,environment,variables,typed,pydantic,dataclass
Classifier: Programming Language :: Python :: 3
Classifier: Programming Language :: Python :: 3.8
Classifier: Programming Language :: Python :: 3.9
Classifier: Programming Language :: Python :: 3.10
Classifier: Programming Language :: Python :: 3.11
Classifier: Programming Language :: Python :: 3.12
Classifier: Operating System :: OS Independent
Classifier: Development Status :: 4 - Beta
Classifier: Intended Audience :: Developers
Classifier: Topic :: Software Development :: Libraries :: Python Modules
Classifier: Topic :: System :: Systems Administration
Requires-Python: >=3.8
License-File: LICENSE
Provides-Extra: test
Requires-Dist: pytest; extra == "test"
Provides-Extra: pydantic
Requires-Dist: pydantic>=1.8.0; extra == "pydantic"
Provides-Extra: yaml
Requires-Dist: pyyaml>=5.4.0; extra == "yaml"
Provides-Extra: all
Requires-Dist: pydantic>=1.8.0; extra == "all"
Requires-Dist: pyyaml>=5.4.0; extra == "all"
Requires-Dist: pytest; extra == "all"
Dynamic: license-file
